<?xml version="1.0" encoding="UTF-8" standalone="yes" ?>
<?codewarrior exportversion="1.0" ideversion="5.0" ?>

<!DOCTYPE EXPORTEDPANEL [
<!ELEMENT EXPORTEDPANEL (NAME, (SETTINGLIST|VALUE))>
<!ELEMENT SETTINGLIST (SETTING+)>
<!ELEMENT SETTING (NAME?, (VALUE|(SETTING+)))>
<!ELEMENT NAME (#PCDATA)>
<!ELEMENT VALUE (#PCDATA)>
]>

<EXPORTEDPANEL>
    <NAME>File Mappings</NAME>
    <SETTINGLIST>
        <SETTING><NAME>FileMappings</NAME>
            <SETTING>
                <SETTING><NAME>FileType</NAME><VALUE>MMLB</VALUE></SETTING>
                <SETTING><NAME>FileExtension</NAME><VALUE></VALUE></SETTING>
                <SETTING><NAME>Compiler</NAME><VALUE>Lib Import 68K</VALUE></SETTING>
                <SETTING><NAME>EditLanguage</NAME><VALUE></VALUE></SETTING>
                <SETTING><NAME>Precompile</NAME><VALUE>false</VALUE></SETTING>
                <SETTING><NAME>Launchable</NAME><VALUE>false</VALUE></SETTING>
                <SETTING><NAME>ResourceFile</NAME><VALUE>false</VALUE></SETTING>
                <SETTING><NAME>IgnoredByMake</NAME><VALUE>false</VALUE></SETTING>
            </SETTING>
            <SETTING>
                <SETTING><NAME>FileType</NAME><VALUE>MPLF</VALUE></SETTING>
                <SETTING><NAME>FileExtension</NAME><VALUE></VALUE></SETTING>
                <SETTING><NAME>Compiler</NAME><VALUE>Lib Import 68K</VALUE></SETTING>
                <SETTING><NAME>EditLanguage</NAME><VALUE></VALUE></SETTING>
                <SETTING><NAME>Precompile</NAME><VALUE>false</VALUE></SETTING>
                <SETTING><NAME>Launchable</NAME><VALUE>false</VALUE></SETTING>
                <SETTING><NAME>ResourceFile</NAME><VALUE>false</VALUE></SETTING>
                <SETTING><NAME>IgnoredByMake</NAME><VALUE>false</VALUE></SETTING>
            </SETTING>
            <SETTING>
                <SETTING><NAME>FileType</NAME><VALUE>TEXT</VALUE></SETTING>
                <SETTING><NAME>FileExtension</NAME><VALUE>.c</VALUE></SETTING>
                <SETTING><NAME>Compiler</NAME><VALUE>MW C/C++ 68K</VALUE></SETTING>
                <SETTING><NAME>EditLanguage</NAME><VALUE>C/C++</VALUE></SETTING>
                <SETTING><NAME>Precompile</NAME><VALUE>false</VALUE></SETTING>
                <SETTING><NAME>Launchable</NAME><VALUE>false</VALUE></SETTING>
                <SETTING><NAME>ResourceFile</NAME><VALUE>false</VALUE></SETTING>
                <SETTING><NAME>IgnoredByMake</NAME><VALUE>false</VALUE></SETTING>
            </SETTING>
            <SETTING>
                <SETTING><NAME>FileType</NAME><VALUE>TEXT</VALUE></SETTING>
                <SETTING><NAME>FileExtension</NAME><VALUE>.c++</VALUE></SETTING>
                <SETTING><NAME>Compiler</NAME><VALUE>MW C/C++ 68K</VALUE></SETTING>
                <SETTING><NAME>EditLanguage</NAME><VALUE>C/C++</VALUE></SETTING>
                <SETTING><NAME>Precompile</NAME><VALUE>false</VALUE></SETTING>
                <SETTING><NAME>Launchable</NAME><VALUE>false</VALUE></SETTING>
                <SETTING><NAME>ResourceFile</NAME><VALUE>false</VALUE></SETTING>
                <SETTING><NAME>IgnoredByMake</NAME><VALUE>false</VALUE></SETTING>
            </SETTING>
            <SETTING>
                <SETTING><NAME>FileType</NAME><VALUE>TEXT</VALUE></SETTING>
                <SETTING><NAME>FileExtension</NAME><VALUE>.cc</VALUE></SETTING>
                <SETTING><NAME>Compiler</NAME><VALUE>MW C/C++ 68K</VALUE></SETTING>
                <SETTING><NAME>EditLanguage</NAME><VALUE>C/C++</VALUE></SETTING>
                <SETTING><NAME>Precompile</NAME><VALUE>false</VALUE></SETTING>
                <SETTING><NAME>Launchable</NAME><VALUE>false</VALUE></SETTING>
                <SETTING><NAME>ResourceFile</NAME><VALUE>false</VALUE></SETTING>
                <SETTING><NAME>IgnoredByMake</NAME><VALUE>false</VALUE></SETTING>
            </SETTING>
            <SETTING>
                <SETTING><NAME>FileType</NAME><VALUE>TEXT</VALUE></SETTING>
                <SETTING><NAME>FileExtension</NAME><VALUE>.cp</VALUE></SETTING>
                <SETTING><NAME>Compiler</NAME><VALUE>MW C/C++ 68K</VALUE></SETTING>
                <SETTING><NAME>EditLanguage</NAME><VALUE>C/C++</VALUE></SETTING>
                <SETTING><NAME>Precompile</NAME><VALUE>false</VALUE></SETTING>
                <SETTING><NAME>Launchable</NAME><VALUE>false</VALUE></SETTING>
                <SETTING><NAME>ResourceFile</NAME><VALUE>false</VALUE></SETTING>
                <SETTING><NAME>IgnoredByMake</NAME><VALUE>false</VALUE></SETTING>
            </SETTING>
            <SETTING>
                <SETTING><NAME>FileType</NAME><VALUE>TEXT</VALUE></SETTING>
                <SETTING><NAME>FileExtension</NAME><VALUE>.cpp</VALUE></SETTING>
                <SETTING><NAME>Compiler</NAME><VALUE>MW C/C++ 68K</VALUE></SETTING>
                <SETTING><NAME>EditLanguage</NAME><VALUE>C/C++</VALUE></SETTING>
                <SETTING><NAME>Precompile</NAME><VALUE>false</VALUE></SETTING>
                <SETTING><NAME>Launchable</NAME><VALUE>false</VALUE></SETTING>
                <SETTING><NAME>ResourceFile</NAME><VALUE>false</VALUE></SETTING>
                <SETTING><NAME>IgnoredByMake</NAME><VALUE>false</VALUE></SETTING>
            </SETTING>
            <SETTING>
                <SETTING><NAME>FileType</NAME><VALUE>TEXT</VALUE></SETTING>
                <SETTING><NAME>FileExtension</NAME><VALUE>.h</VALUE></SETTING>
                <SETTING><NAME>Compiler</NAME><VALUE>MW C/C++ 68K</VALUE></SETTING>
                <SETTING><NAME>EditLanguage</NAME><VALUE>C/C++</VALUE></SETTING>
                <SETTING><NAME>Precompile</NAME><VALUE>false</VALUE></SETTING>
                <SETTING><NAME>Launchable</NAME><VALUE>false</VALUE></SETTING>
                <SETTING><NAME>ResourceFile</NAME><VALUE>false</VALUE></SETTING>
                <SETTING><NAME>IgnoredByMake</NAME><VALUE>true</VALUE></SETTING>
            </SETTING>
            <SETTING>
                <SETTING><NAME>FileType</NAME><VALUE>TEXT</VALUE></SETTING>
                <SETTING><NAME>FileExtension</NAME><VALUE>.pch</VALUE></SETTING>
                <SETTING><NAME>Compiler</NAME><VALUE>MW C/C++ 68K</VALUE></SETTING>
                <SETTING><NAME>EditLanguage</NAME><VALUE>C/C++</VALUE></SETTING>
                <SETTING><NAME>Precompile</NAME><VALUE>true</VALUE></SETTING>
                <SETTING><NAME>Launchable</NAME><VALUE>false</VALUE></SETTING>
                <SETTING><NAME>ResourceFile</NAME><VALUE>false</VALUE></SETTING>
                <SETTING><NAME>IgnoredByMake</NAME><VALUE>false</VALUE></SETTING>
            </SETTING>
            <SETTING>
                <SETTING><NAME>FileType</NAME><VALUE>TEXT</VALUE></SETTING>
                <SETTING><NAME>FileExtension</NAME><VALUE>.pch++</VALUE></SETTING>
                <SETTING><NAME>Compiler</NAME><VALUE>MW C/C++ 68K</VALUE></SETTING>
                <SETTING><NAME>EditLanguage</NAME><VALUE>C/C++</VALUE></SETTING>
                <SETTING><NAME>Precompile</NAME><VALUE>true</VALUE></SETTING>
                <SETTING><NAME>Launchable</NAME><VALUE>false</VALUE></SETTING>
                <SETTING><NAME>ResourceFile</NAME><VALUE>false</VALUE></SETTING>
                <SETTING><NAME>IgnoredByMake</NAME><VALUE>false</VALUE></SETTING>
            </SETTING>
            <SETTING>
                <SETTING><NAME>FileType</NAME><VALUE>TEXT</VALUE></SETTING>
                <SETTING><NAME>FileExtension</NAME><VALUE>.rcp</VALUE></SETTING>
                <SETTING><NAME>Compiler</NAME><VALUE>PilRC Compiler Adapter</VALUE></SETTING>
                <SETTING><NAME>EditLanguage</NAME><VALUE>PilRC</VALUE></SETTING>
                <SETTING><NAME>Precompile</NAME><VALUE>false</VALUE></SETTING>
                <SETTING><NAME>Launchable</NAME><VALUE>false</VALUE></SETTING>
                <SETTING><NAME>ResourceFile</NAME><VALUE>false</VALUE></SETTING>
                <SETTING><NAME>IgnoredByMake</NAME><VALUE>false</VALUE></SETTING>
            </SETTING>
            <SETTING>
                <SETTING><NAME>FileType</NAME><VALUE>TEXT</VALUE></SETTING>
                <SETTING><NAME>FileExtension</NAME><VALUE>.seg</VALUE></SETTING>
                <SETTING><NAME>Compiler</NAME><VALUE></VALUE></SETTING>
                <SETTING><NAME>EditLanguage</NAME><VALUE></VALUE></SETTING>
                <SETTING><NAME>Precompile</NAME><VALUE>false</VALUE></SETTING>
                <SETTING><NAME>Launchable</NAME><VALUE>false</VALUE></SETTING>
                <SETTING><NAME>ResourceFile</NAME><VALUE>false</VALUE></SETTING>
                <SETTING><NAME>IgnoredByMake</NAME><VALUE>false</VALUE></SETTING>
            </SETTING>
            <SETTING>
                <SETTING><NAME>FileType</NAME><VALUE>TEXT</VALUE></SETTING>
                <SETTING><NAME>FileExtension</NAME><VALUE>.txt</VALUE></SETTING>
                <SETTING><NAME>Compiler</NAME><VALUE></VALUE></SETTING>
                <SETTING><NAME>EditLanguage</NAME><VALUE></VALUE></SETTING>
                <SETTING><NAME>Precompile</NAME><VALUE>false</VALUE></SETTING>
                <SETTING><NAME>Launchable</NAME><VALUE>false</VALUE></SETTING>
                <SETTING><NAME>ResourceFile</NAME><VALUE>false</VALUE></SETTING>
                <SETTING><NAME>IgnoredByMake</NAME><VALUE>true</VALUE></SETTING>
            </SETTING>
            <SETTING>
                <SETTING><NAME>FileExtension</NAME><VALUE>.bin</VALUE></SETTING>
                <SETTING><NAME>Compiler</NAME><VALUE>Palm OS Resource Importer</VALUE></SETTING>
                <SETTING><NAME>EditLanguage</NAME><VALUE></VALUE></SETTING>
                <SETTING><NAME>Precompile</NAME><VALUE>false</VALUE></SETTING>
                <SETTING><NAME>Launchable</NAME><VALUE>false</VALUE></SETTING>
                <SETTING><NAME>ResourceFile</NAME><VALUE>true</VALUE></SETTING>
                <SETTING><NAME>IgnoredByMake</NAME><VALUE>false</VALUE></SETTING>
            </SETTING>
            <SETTING>
                <SETTING><NAME>FileExtension</NAME><VALUE>.bmp</VALUE></SETTING>
                <SETTING><NAME>Compiler</NAME><VALUE>PilRC Compiler Adapter</VALUE></SETTING>
                <SETTING><NAME>EditLanguage</NAME><VALUE></VALUE></SETTING>
                <SETTING><NAME>Precompile</NAME><VALUE>false</VALUE></SETTING>
                <SETTING><NAME>Launchable</NAME><VALUE>true</VALUE></SETTING>
                <SETTING><NAME>ResourceFile</NAME><VALUE>false</VALUE></SETTING>
                <SETTING><NAME>IgnoredByMake</NAME><VALUE>true</VALUE></SETTING>
            </SETTING>
            <SETTING>
                <SETTING><NAME>FileExtension</NAME><VALUE>.doc</VALUE></SETTING>
                <SETTING><NAME>Compiler</NAME><VALUE></VALUE></SETTING>
                <SETTING><NAME>EditLanguage</NAME><VALUE></VALUE></SETTING>
                <SETTING><NAME>Precompile</NAME><VALUE>false</VALUE></SETTING>
                <SETTING><NAME>Launchable</NAME><VALUE>true</VALUE></SETTING>
                <SETTING><NAME>ResourceFile</NAME><VALUE>false</VALUE></SETTING>
                <SETTING><NAME>IgnoredByMake</NAME><VALUE>true</VALUE></SETTING>
            </SETTING>
            <SETTING>
                <SETTING><NAME>FileExtension</NAME><VALUE>.pbitm</VALUE></SETTING>
                <SETTING><NAME>Compiler</NAME><VALUE>PilRC Compiler Adapter</VALUE></SETTING>
                <SETTING><NAME>EditLanguage</NAME><VALUE></VALUE></SETTING>
                <SETTING><NAME>Precompile</NAME><VALUE>false</VALUE></SETTING>
                <SETTING><NAME>Launchable</NAME><VALUE>true</VALUE></SETTING>
                <SETTING><NAME>ResourceFile</NAME><VALUE>false</VALUE></SETTING>
                <SETTING><NAME>IgnoredByMake</NAME><VALUE>true</VALUE></SETTING>
            </SETTING>
            <SETTING>
                <SETTING><NAME>FileExtension</NAME><VALUE>.pbm</VALUE></SETTING>
                <SETTING><NAME>Compiler</NAME><VALUE>PilRC Compiler Adapter</VALUE></SETTING>
                <SETTING><NAME>EditLanguage</NAME><VALUE></VALUE></SETTING>
                <SETTING><NAME>Precompile</NAME><VALUE>false</VALUE></SETTING>
                <SETTING><NAME>Launchable</NAME><VALUE>true</VALUE></SETTING>
                <SETTING><NAME>ResourceFile</NAME><VALUE>false</VALUE></SETTING>
                <SETTING><NAME>IgnoredByMake</NAME><VALUE>true</VALUE></SETTING>
            </SETTING>
            <SETTING>
                <SETTING><NAME>FileExtension</NAME><VALUE>.pgm</VALUE></SETTING>
                <SETTING><NAME>Compiler</NAME><VALUE>PilRC Compiler Adapter</VALUE></SETTING>
                <SETTING><NAME>EditLanguage</NAME><VALUE></VALUE></SETTING>
                <SETTING><NAME>Precompile</NAME><VALUE>false</VALUE></SETTING>
                <SETTING><NAME>Launchable</NAME><VALUE>true</VALUE></SETTING>
                <SETTING><NAME>ResourceFile</NAME><VALUE>false</VALUE></SETTING>
                <SETTING><NAME>IgnoredByMake</NAME><VALUE>true</VALUE></SETTING>
            </SETTING>
            <SETTING>
                <SETTING><NAME>FileExtension</NAME><VALUE>.pnm</VALUE></SETTING>
                <SETTING><NAME>Compiler</NAME><VALUE>PilRC Compiler Adapter</VALUE></SETTING>
                <SETTING><NAME>EditLanguage</NAME><VALUE></VALUE></SETTING>
                <SETTING><NAME>Precompile</NAME><VALUE>false</VALUE></SETTING>
                <SETTING><NAME>Launchable</NAME><VALUE>true</VALUE></SETTING>
                <SETTING><NAME>ResourceFile</NAME><VALUE>false</VALUE></SETTING>
                <SETTING><NAME>IgnoredByMake</NAME><VALUE>true</VALUE></SETTING>
            </SETTING>
            <SETTING>
                <SETTING><NAME>FileExtension</NAME><VALUE>.ppm</VALUE></SETTING>
                <SETTING><NAME>Compiler</NAME><VALUE>PilRC Compiler Adapter</VALUE></SETTING>
                <SETTING><NAME>EditLanguage</NAME><VALUE></VALUE></SETTING>
                <SETTING><NAME>Precompile</NAME><VALUE>false</VALUE></SETTING>
                <SETTING><NAME>Launchable</NAME><VALUE>true</VALUE></SETTING>
                <SETTING><NAME>ResourceFile</NAME><VALUE>false</VALUE></SETTING>
                <SETTING><NAME>IgnoredByMake</NAME><VALUE>true</VALUE></SETTING>
            </SETTING>
            <SETTING>
                <SETTING><NAME>FileExtension</NAME><VALUE>.prc</VALUE></SETTING>
                <SETTING><NAME>Compiler</NAME><VALUE>Palm OS Resource Importer</VALUE></SETTING>
                <SETTING><NAME>EditLanguage</NAME><VALUE></VALUE></SETTING>
                <SETTING><NAME>Precompile</NAME><VALUE>false</VALUE></SETTING>
                <SETTING><NAME>Launchable</NAME><VALUE>false</VALUE></SETTING>
                <SETTING><NAME>ResourceFile</NAME><VALUE>true</VALUE></SETTING>
                <SETTING><NAME>IgnoredByMake</NAME><VALUE>false</VALUE></SETTING>
            </SETTING>
            <SETTING>
                <SETTING><NAME>FileExtension</NAME><VALUE>.ro</VALUE></SETTING>
                <SETTING><NAME>Compiler</NAME><VALUE>Palm OS Resource Importer</VALUE></SETTING>
                <SETTING><NAME>EditLanguage</NAME><VALUE></VALUE></SETTING>
                <SETTING><NAME>Precompile</NAME><VALUE>false</VALUE></SETTING>
                <SETTING><NAME>Launchable</NAME><VALUE>false</VALUE></SETTING>
                <SETTING><NAME>ResourceFile</NAME><VALUE>true</VALUE></SETTING>
                <SETTING><NAME>IgnoredByMake</NAME><VALUE>false</VALUE></SETTING>
            </SETTING>
            <SETTING>
                <SETTING><NAME>FileExtension</NAME><VALUE>.xbm</VALUE></SETTING>
                <SETTING><NAME>Compiler</NAME><VALUE>PilRC Compiler Adapter</VALUE></SETTING>
                <SETTING><NAME>EditLanguage</NAME><VALUE></VALUE></SETTING>
                <SETTING><NAME>Precompile</NAME><VALUE>false</VALUE></SETTING>
                <SETTING><NAME>Launchable</NAME><VALUE>true</VALUE></SETTING>
                <SETTING><NAME>ResourceFile</NAME><VALUE>false</VALUE></SETTING>
                <SETTING><NAME>IgnoredByMake</NAME><VALUE>true</VALUE></SETTING>
            </SETTING>
        </SETTING>
    </SETTINGLIST>
</EXPORTEDPANEL>
